<?xml version="1.0" encoding="UTF-8" ?>
<!DOCTYPE mapper PUBLIC "-//mybatis.org//DTD Mapper 3.0//EN" "http://mybatis.org/dtd/mybatis-3-mapper.dtd">

<mapper namespace="org.umeframework.quickstart.sample.entity">
  <!-- 参加该唱片录音的艺术家信息管理表 [ALBUM_CONTRIBUTOR] -->

  <!-- Insert -->
  <insert id="ALBUM_CONTRIBUTOR_INSERT" parameterType="org.umeframework.quickstart.sample.entity.AlbumContributorDto">
    INSERT INTO ALBUM_CONTRIBUTOR (
      ALBUM_ID
      ,TRACK_NO
      ,CONTRIBUTOR
      ,COMMENT
      ,CREATE_AUTHOR
      ,CREATE_DATETIME
      ,UPDATE_AUTHOR
      ,UPDATE_DATETIME
    ) VALUES (
      #{albumId}
      ,#{trackNo}
      ,#{contributor}
      ,#{comment}
      ,#{createAuthor}
      ,current_timestamp()
      ,#{updateAuthor}
      ,current_timestamp()
    )
  </insert>
  
  <!-- Update -->
  <update id="ALBUM_CONTRIBUTOR_UPDATE" parameterType="org.umeframework.quickstart.sample.entity.AlbumContributorDto">
    UPDATE ALBUM_CONTRIBUTOR
    <set>
      UPDATE_DATETIME = current_timestamp(),
      <if test="comment!=null">COMMENT = #{comment},</if>
      <if test="createAuthor!=null">CREATE_AUTHOR = #{createAuthor},</if>
      <if test="createDatetime!=null">CREATE_DATETIME = #{createDatetime},</if>
      <if test="updateAuthor!=null">UPDATE_AUTHOR = #{updateAuthor},</if>
    </set>
    WHERE 
       ALBUM_ID = #{albumId}
       AND TRACK_NO = #{trackNo}
       AND CONTRIBUTOR = #{contributor}
      <if test="updateDatetime!=null"> AND UPDATE_DATETIME = #{updateDatetime}</if>
  </update>
  
  <!-- Update Any -->
  <update id="ALBUM_CONTRIBUTOR_UPDATE_ANY" parameterType="org.umeframework.quickstart.sample.entity.AlbumContributorDto">
    UPDATE ALBUM_CONTRIBUTOR
    <set>
      UPDATE_DATETIME = current_timestamp(),
      <if test="comment!=null">COMMENT = #{comment},</if>
      <if test="createAuthor!=null">CREATE_AUTHOR = #{createAuthor},</if>
      <if test="createDatetime!=null">CREATE_DATETIME = #{createDatetime},</if>
      <if test="updateAuthor!=null">UPDATE_AUTHOR = #{updateAuthor},</if>
    </set>
    WHERE 1 = 1 
      <if test="albumId != null">AND ALBUM_ID = #{albumId}</if>
      <if test="trackNo != null">AND TRACK_NO = #{trackNo}</if>
      <if test="contributor != null">AND CONTRIBUTOR = #{contributor}</if>
      <if test="comment != null">AND COMMENT = #{comment}</if>
      <if test="createAuthor != null">AND CREATE_AUTHOR = #{createAuthor}</if>
      <if test="updateAuthor != null">AND UPDATE_AUTHOR = #{updateAuthor}</if>
      <if test="createDatetime != null">AND CREATE_DATETIME = #{createDatetime}</if>
      <if test="updateDatetime != null">AND UPDATE_DATETIME = #{updateDatetime}</if>
  </update>

  <!-- Update Fully -->
  <update id="ALBUM_CONTRIBUTOR_UPDATE_FULLY" parameterType="org.umeframework.quickstart.sample.entity.AlbumContributorDto">
    UPDATE ALBUM_CONTRIBUTOR
    SET
      COMMENT = #{comment}
      ,CREATE_AUTHOR = #{createAuthor}
      ,CREATE_DATETIME = #{createDatetime}
      ,UPDATE_AUTHOR = #{updateAuthor}
      ,UPDATE_DATETIME = current_timestamp() 
    WHERE 
       ALBUM_ID = #{albumId}
       AND TRACK_NO = #{trackNo}
       AND CONTRIBUTOR = #{contributor}
      <if test="updateDatetime!=null"> AND UPDATE_DATETIME = #{updateDatetime}</if>
  </update>
  
  <!-- Delete -->
  <delete id="ALBUM_CONTRIBUTOR_DELETE" parameterType="org.umeframework.quickstart.sample.entity.AlbumContributorDto">
    DELETE FROM ALBUM_CONTRIBUTOR
    WHERE
       ALBUM_ID = #{albumId}
       AND TRACK_NO = #{trackNo}
       AND CONTRIBUTOR = #{contributor}
      <if test="updateDatetime!=null"> AND UPDATE_DATETIME = #{updateDatetime}</if>
  </delete>

  <!-- Delete Any -->
  <delete id="ALBUM_CONTRIBUTOR_DELETE_ANY" parameterType="org.umeframework.quickstart.sample.entity.AlbumContributorDto">
    DELETE FROM ALBUM_CONTRIBUTOR
    WHERE 1 = 1 
      <if test="albumId != null">AND ALBUM_ID = #{albumId}</if>
      <if test="trackNo != null">AND TRACK_NO = #{trackNo}</if>
      <if test="contributor != null">AND CONTRIBUTOR = #{contributor}</if>
      <if test="comment != null">AND COMMENT = #{comment}</if>
      <if test="createAuthor != null">AND CREATE_AUTHOR = #{createAuthor}</if>
      <if test="updateAuthor != null">AND UPDATE_AUTHOR = #{updateAuthor}</if>
      <if test="createDatetime != null">AND CREATE_DATETIME = #{createDatetime}</if>
      <if test="updateDatetime != null">AND UPDATE_DATETIME = #{updateDatetime}</if>
  </delete>
  
  <!-- Find -->
  <select id="ALBUM_CONTRIBUTOR_FIND" resultType="org.umeframework.quickstart.sample.entity.AlbumContributorDto">
    SELECT
      ALBUM_ID AS "albumId" 
      ,TRACK_NO AS "trackNo" 
      ,CONTRIBUTOR AS "contributor" 
      ,COMMENT AS "comment" 
      ,CREATE_AUTHOR AS "createAuthor"
      ,CREATE_DATETIME AS "createDatetime"
      ,UPDATE_AUTHOR AS "updateAuthor"
      ,UPDATE_DATETIME AS "updateDatetime"
    FROM ALBUM_CONTRIBUTOR
    WHERE
       ALBUM_ID = #{albumId} 
       AND TRACK_NO = #{trackNo} 
       AND CONTRIBUTOR = #{contributor} 
  </select>

  <!-- Find For Update -->
  <select id="ALBUM_CONTRIBUTOR_FIND_FOR_UPDATE" resultType="org.umeframework.quickstart.sample.entity.AlbumContributorDto">
    SELECT
      ALBUM_ID AS "albumId"
      ,TRACK_NO AS "trackNo"
      ,CONTRIBUTOR AS "contributor"
      ,COMMENT AS "comment"
      ,CREATE_AUTHOR AS "createAuthor"
      ,CREATE_DATETIME AS "createDatetime"
      ,UPDATE_AUTHOR AS "updateAuthor"
      ,UPDATE_DATETIME AS "updateDatetime"
    FROM ALBUM_CONTRIBUTOR
    WHERE
       ALBUM_ID = #{albumId} 
       AND TRACK_NO = #{trackNo} 
       AND CONTRIBUTOR = #{contributor} 
    FOR UPDATE
  </select>

  <!-- Find List -->
  <select id="ALBUM_CONTRIBUTOR_FIND_LIST" resultType="org.umeframework.quickstart.sample.entity.AlbumContributorDto">
    SELECT
      ALBUM_ID AS "albumId"
      ,TRACK_NO AS "trackNo"
      ,CONTRIBUTOR AS "contributor"
      ,COMMENT AS "comment"
      ,CREATE_AUTHOR AS "createAuthor"
      ,CREATE_DATETIME AS "createDatetime"
      ,UPDATE_AUTHOR AS "updateAuthor"
      ,UPDATE_DATETIME AS "updateDatetime"
    FROM ALBUM_CONTRIBUTOR
    WHERE 1 = 1 
      <if test="albumId != null">AND ALBUM_ID = #{albumId}</if>
      <if test="trackNo != null">AND TRACK_NO = #{trackNo}</if>
      <if test="contributor != null">AND CONTRIBUTOR = #{contributor}</if>
      <if test="comment != null">AND COMMENT = #{comment}</if>
      <if test="createAuthor != null">AND CREATE_AUTHOR = #{createAuthor}</if>
      <if test="updateAuthor != null">AND UPDATE_AUTHOR = #{updateAuthor}</if>
      <if test="createDatetime != null">AND CREATE_DATETIME = #{createDatetime}</if>
      <if test="updateDatetime != null">AND UPDATE_DATETIME = #{updateDatetime}</if>
      <if test="theOrderByCondition != null"> ORDER BY ${theOrderByCondition}</if>
      <if test="theGroupByCondition != null"> GROUP BY ${theGroupByCondition}</if>
      <if test="theFetchSize != null">LIMIT ${theFetchStart}, ${theFetchSize}</if>
  </select>

  <!-- Find List Like -->
  <select id="ALBUM_CONTRIBUTOR_FIND_LIST_LIKE" resultType="org.umeframework.quickstart.sample.entity.AlbumContributorDto">
    SELECT
      ALBUM_ID AS "albumId"
      ,TRACK_NO AS "trackNo"
      ,CONTRIBUTOR AS "contributor"
      ,COMMENT AS "comment"
      ,CREATE_AUTHOR AS "createAuthor"
      ,CREATE_DATETIME AS "createDatetime"
      ,UPDATE_AUTHOR AS "updateAuthor"
      ,UPDATE_DATETIME AS "updateDatetime"
    FROM ALBUM_CONTRIBUTOR
    WHERE 1 = 1 
      <if test="albumId != null">AND ALBUM_ID LIKE CONCAT('%', #{albumId}, '%')</if>
      <if test="trackNo != null">AND TRACK_NO LIKE CONCAT('%', #{trackNo}, '%')</if>
      <if test="contributor != null">AND CONTRIBUTOR LIKE CONCAT('%', #{contributor}, '%')</if>
      <if test="comment != null">AND COMMENT LIKE CONCAT('%', #{comment}, '%')</if>
      <if test="createAuthor != null">AND CREATE_AUTHOR LIKE CONCAT('%', #{createAuthor}, '%')</if>
      <if test="updateAuthor != null">AND UPDATE_AUTHOR LIKE CONCAT('%', #{updateAuthor}, '%')</if>
      <if test="createDatetime != null">AND CREATE_DATETIME LIKE CONCAT('%', #{createDatetime}, '%')</if>
      <if test="updateDatetime != null">AND UPDATE_DATETIME LIKE CONCAT('%', #{updateDatetime}, '%')</if>
      <if test="theOrderByCondition != null"> ORDER BY ${theOrderByCondition}</if>
      <if test="theGroupByCondition != null"> GROUP BY ${theGroupByCondition}</if>
      <if test="theFetchSize != null">LIMIT ${theFetchStart}, ${theFetchSize}</if>
  </select>
  
  <!-- Count -->
  <select id="ALBUM_CONTRIBUTOR_COUNT" resultType="java.lang.Integer">
    SELECT count(*)
    FROM ALBUM_CONTRIBUTOR
    WHERE 1 = 1 
      <if test="albumId != null">AND ALBUM_ID = #{albumId}</if>
      <if test="trackNo != null">AND TRACK_NO = #{trackNo}</if>
      <if test="contributor != null">AND CONTRIBUTOR = #{contributor}</if>
      <if test="comment != null">AND COMMENT = #{comment}</if>
  </select>


</mapper>

